CHANGES.md
bovine_process/__init__.py
bovine_process/common/__init__.py
bovine_process/common/interactions.py
bovine_process/common/test_interactions.py
bovine_process/incoming/__init__.py
bovine_process/incoming/following.py
bovine_process/incoming/handle_update.py
bovine_process/incoming/incoming_delete.py
bovine_process/incoming/store_incoming.py
bovine_process/incoming/test_following.py
bovine_process/incoming/test_handle_update.py
bovine_process/incoming/test_store_incoming.py
bovine_process/outgoing/__init__.py
bovine_process/outgoing/following.py
bovine_process/outgoing/outgoing_delete.py
bovine_process/outgoing/outgoing_update.py
bovine_process/outgoing/store_outgoing.py
bovine_process/outgoing/test_following.py
bovine_process/outgoing/test_outgoing_update.py
bovine_process/outgoing/test_update_id.py
bovine_process/outgoing/update_id.py
bovine_process/send_item.py
bovine_process/test_types.py
bovine_process/types.py
bovine_process/utils/__init__.py
bovine_process/utils/test_by_activity_type.py
bovine_process/utils/test_processor_list.py
bovine_propan/__init__.py
bovine_propan/actor.py
bovine_propan/broker.py
bovine_propan/enqueuers.py
bovine_propan/exchanges.py
bovine_propan/test_broker.py
bovine_propan/test_enqueuers.py
bovine_propan/types.py
bovine_process-0.5.19.dist-info/METADATA
bovine_process-0.5.19.dist-info/WHEEL
bovine_process-0.5.19.dist-info/RECORD
