Metadata-Version: 2.1
Name: bovine-process
Version: 0.5.19
Summary: Processing of Side Effects of ActivityPub Activities for an ActivityPub Server
Home-page: https://codeberg.org/bovine/bovine
License: MIT
Author: Helge
Author-email: helge.krueger@gmail.com
Requires-Python: >=3.11,<4.0
Classifier: Intended Audience :: Developers
Classifier: License :: OSI Approved :: MIT License
Classifier: Programming Language :: Python :: 3
Classifier: Programming Language :: Python :: 3.11
Classifier: Programming Language :: Python :: 3.11
Classifier: Programming Language :: Python :: 3.12
Classifier: Topic :: Communications
Classifier: Topic :: Software Development :: Libraries :: Python Modules
Provides-Extra: propan
Requires-Dist: bovine-store (>=0.5.19,<0.6.0)
Requires-Dist: faststream[rabbit] (>=0.5.0,<0.6.0) ; extra == "propan"
Project-URL: Documentation, https://bovine-process.readthedocs.io/en/latest/
Project-URL: Repository, https://codeberg.org/bovine/bovine
